PlanaPY/PlanaPY.py
PlanaPY/__init__.py
PlanaPY-0.2.8.dist-info/License.txt
PlanaPY-0.2.8.dist-info/METADATA
PlanaPY-0.2.8.dist-info/WHEEL
PlanaPY-0.2.8.dist-info/top_level.txt
PlanaPY-0.2.8.dist-info/RECORD
